{
  "openapi": "3.0.1",
  "info": {
    "title": "Content Playback Session API",
    "description": "This API enables the creation and management of playback sessions for streaming content, allowing users to resume their viewing experiences across devices while syncing progress. It provides endpoints to track session progress and handle user-specific interactions.",
    "version": "1.0",
    "extensions": {
      "x-oas-type": "Runtime"
    }
  },
  "servers": [
    {
      "url": "https://stage-data-gujl.apiwiz.io/v1/streaming",
      "description": "Sandbox server",
      "variables": {},
      "x-schema": "https://",
      "x-name": "Sandbox server",
      "x-environmentName": "DEV",
      "x-hide": false,
      "x-environmentId": "688884305134cd49a9bcfec3",
      "x-basePath": "/v1/streaming"
    }
  ],
  "paths": {
    "/playback/content/progress/sync/device/resume/session/create": {
      "post": {
        "tags": [
          "Playback"
        ],
        "summary": "Create Playback Resume Session",
        "description": "This operation allows clients to create a new playback resume session for a specific device. Users must provide their user ID and device ID in the request headers, along with the necessary content details in the request body. A successful response will yield session details for continuing playback seamlessly.",
        "operationId": "createPlaybackResumeSession",
        "parameters": [
          {
            "$ref": "#/components/parameters/X-User-Id"
          },
          {
            "$ref": "#/components/parameters/X-Device-Id"
          },
          {
            "$ref": "#/components/parameters/Content-Type"
          },
          {
            "$ref": "#/components/parameters/parentspanid"
          },
          {
            "$ref": "#/components/parameters/Authorization"
          },
          {
            "$ref": "#/components/parameters/x-mock-response"
          }
        ],
        "requestBody": {
          "content": {
            "application/json": {
              "schema": {
                "$ref": "#/components/schemas/CreatePlaybackResumeSessionRequest"
              }
            }
          }
        },
        "responses": {
          "400": {
            "description": "Invalid request parameters",
            "headers": {
              "Date": {
                "$ref": "#/components/headers/Date"
              },
              "X-Trace-Id": {
                "$ref": "#/components/headers/X-Trace-Id"
              },
              "Content-Type": {
                "$ref": "#/components/headers/Content-Type"
              }
            },
            "content": {
              "application/json": {
                "schema": {
                  "$ref": "#/components/schemas/CreatePlaybackResumeSessionResponse_400"
                }
              }
            }
          },
          "500": {
            "description": "Internal server error",
            "headers": {
              "Date": {
                "$ref": "#/components/headers/Date"
              },
              "X-Trace-Id": {
                "$ref": "#/components/headers/X-Trace-Id"
              },
              "Content-Type": {
                "$ref": "#/components/headers/Content-Type"
              }
            },
            "content": {
              "application/json": {
                "schema": {
                  "$ref": "#/components/schemas/CreatePlaybackResumeSessionResponse_500"
                }
              }
            }
          },
          "200": {
            "description": "Resume session created successfully",
            "headers": {
              "Date": {
                "$ref": "#/components/headers/Date"
              },
              "X-Trace-Id": {
                "$ref": "#/components/headers/X-Trace-Id"
              },
              "Content-Type": {
                "$ref": "#/components/headers/Content-Type"
              }
            },
            "content": {
              "application/json": {
                "schema": {
                  "$ref": "#/components/schemas/CreatePlaybackResumeSessionResponse_200"
                }
              }
            }
          }
        },
        "callbacks": {},
        "security": [],
        "servers": []
      },
      "servers": [],
      "parameters": []
    }
  },
  "components": {
    "schemas": {
      "CreatePlaybackResumeSessionResponse_400": {
        "type": "object",
        "properties": {
          "error": {
            "type": "string",
            "example": "PLAYBACK_SESSION_FAILED"
          },
          "code": {
            "type": "integer",
            "format": "int32",
            "example": 400
          },
          "details": {
            "type": "array",
            "example": [
              "Content MOV-UNAVAIL-999 is not available in your region",
              "progressSeconds exceeds content duration",
              "deviceId is required",
              "User has reached maximum simultaneous stream limit of 4"
            ],
            "items": {
              "type": "string",
              "example": "ddPGiSXc8zzDkOHh1QZuYivJFDtDa1UunaWhzao2w1dfFFjWUVV7NWb"
            }
          },
          "timestamp": {
            "type": "string",
            "example": "2026-06-08T10:00:00Z"
          }
        },
        "example": {
          "error": "PLAYBACK_SESSION_FAILED",
          "code": 400,
          "details": [
            "Content MOV-UNAVAIL-999 is not available in your region",
            "progressSeconds exceeds content duration",
            "deviceId is required",
            "User has reached maximum simultaneous stream limit of 4"
          ],
          "timestamp": "2026-06-08T10:00:00Z"
        }
      },
      "CreatePlaybackResumeSessionResponse_500": {
        "type": "object",
        "properties": {
          "error": {
            "type": "string",
            "example": "CDN_STREAM_UNAVAILABLE"
          },
          "code": {
            "type": "integer",
            "format": "int32",
            "example": 500
          },
          "message": {
            "type": "string",
            "example": "Content delivery network is experiencing high latency. Please retry or switch to a lower quality."
          },
          "incidentId": {
            "type": "string",
            "example": "INC-STRM-2026-0822"
          },
          "retryAfter": {
            "type": "integer",
            "format": "int32",
            "example": 20
          },
          "timestamp": {
            "type": "string",
            "example": "2026-06-08T10:00:00Z"
          }
        },
        "example": {
          "error": "CDN_STREAM_UNAVAILABLE",
          "code": 500,
          "message": "Content delivery network is experiencing high latency. Please retry or switch to a lower quality.",
          "incidentId": "INC-STRM-2026-0822",
          "retryAfter": 20,
          "timestamp": "2026-06-08T10:00:00Z"
        }
      },
      "CreatePlaybackResumeSessionRequest": {
        "type": "object",
        "properties": {
          "userId": {
            "type": "string",
            "example": "ehVt4SAfT4iQ"
          },
          "contentId": {
            "type": "string",
            "example": "k88PVvKmb"
          },
          "episodeId": {
            "type": "string",
            "example": "j2fkicYSu"
          },
          "deviceId": {
            "type": "string",
            "example": "YaQ3k3HAXw9fUY"
          },
          "progressSeconds": {
            "type": "integer",
            "format": "int32",
            "example": 17
          },
          "totalSeconds": {
            "type": "integer",
            "format": "int32",
            "example": 59
          },
          "quality": {
            "type": "string",
            "example": "Hq"
          },
          "audioTrack": {
            "type": "string",
            "example": "hw"
          },
          "subtitleTrack": {
            "type": "string",
            "example": "vi"
          },
          "timestamp": {
            "type": "string",
            "example": "nZBwxnQs6ULVW9ZHUB3K"
          }
        },
        "example": "{\n  \"userId\" : \"ehVt4SAfT4iQ\",\n  \"contentId\" : \"k88PVvKmb\",\n  \"episodeId\" : \"j2fkicYSu\",\n  \"deviceId\" : \"YaQ3k3HAXw9fUY\",\n  \"progressSeconds\" : 17,\n  \"totalSeconds\" : 59,\n  \"quality\" : \"Hq\",\n  \"audioTrack\" : \"hw\",\n  \"subtitleTrack\" : \"vi\",\n  \"timestamp\" : \"nZBwxnQs6ULVW9ZHUB3K\"\n}"
      },
      "CreatePlaybackResumeSessionResponse_200": {
        "type": "object",
        "example": {}
      }
    },
    "parameters": {
      "X-User-Id": {
        "name": "X-User-Id",
        "in": "header",
        "required": false,
        "style": "simple",
        "explode": false,
        "schema": {
          "type": "string",
          "example": "USR-VFX-9921"
        },
        "example": "USR-VFX-9921"
      },
      "X-Device-Id": {
        "name": "X-Device-Id",
        "in": "header",
        "required": false,
        "style": "simple",
        "explode": false,
        "schema": {
          "type": "string",
          "example": "DEVICE-TV-8821"
        },
        "example": "DEVICE-TV-8821"
      },
      "Content-Type": {
        "name": "Content-Type",
        "in": "header",
        "required": false,
        "style": "simple",
        "explode": false,
        "schema": {
          "type": "string",
          "example": "application/json"
        },
        "example": "application/json"
      },
      "parentspanid": {
        "name": "parentspanid",
        "in": "header",
        "required": false,
        "style": "simple",
        "explode": false,
        "schema": {
          "type": "string",
          "example": "48c44b11a6ca4ec386d8cabbc4daead3b8b94f8684c841f4"
        },
        "example": "48c44b11a6ca4ec386d8cabbc4daead3b8b94f8684c841f4"
      },
      "Authorization": {
        "name": "Authorization",
        "in": "header",
        "required": false,
        "style": "simple",
        "explode": false,
        "schema": {
          "type": "string",
          "example": "Bearer viewer-auth-token"
        },
        "example": "Bearer viewer-auth-token"
      },
      "x-mock-response": {
        "name": "x-mock-response",
        "in": "header",
        "description": "Controls x-mock-response response status",
        "required": false,
        "style": "simple",
        "explode": false,
        "schema": {
          "type": "string",
          "enum": [
            "bad_request",
            "server_error",
            "success"
          ]
        }
      }
    },
    "headers": {
      "Date": {
        "style": "simple",
        "explode": false,
        "schema": {
          "type": "string",
          "example": "Mon, 08 Jun 2026 10:00:00 GMT"
        },
        "example": "Mon, 08 Jun 2026 10:00:00 GMT"
      },
      "X-Trace-Id": {
        "style": "simple",
        "explode": false,
        "schema": {
          "type": "string",
          "example": "a0bacccba87e4236bef8fc26cb6fa181b9796633f67d44e0"
        },
        "example": "a0bacccba87e4236bef8fc26cb6fa181b9796633f67d44e0"
      },
      "Content-Type": {
        "style": "simple",
        "explode": false,
        "schema": {
          "type": "string",
          "example": "application/json"
        },
        "example": "application/json"
      }
    }
  }
}