{
  "openapi": "3.0.1",
  "info": {
    "title": "Fund Transfer API",
    "description": "The Fund Transfer API enables users to initiate and manage monetary transfers securely and efficiently. This API provides endpoints for submitting transfer requests, handling responses for various scenarios including success and errors, and ensuring proper authorization for transactions.",
    "version": "1.0",
    "extensions": {
      "x-oas-type": "Runtime"
    }
  },
  "servers": [
    {
      "url": "https://stage-data-gujl.apiwiz.io/v1/payments",
      "description": "Sandbox server",
      "variables": {},
      "x-schema": "https://",
      "x-name": "Sandbox server",
      "x-environmentName": "DEV",
      "x-hide": false,
      "x-environmentId": "688884305134cd49a9bcfec3",
      "x-basePath": "/v1/payments"
    }
  ],
  "paths": {
    "/transfer": {
      "post": {
        "tags": [
          "Fund Transfer"
        ],
        "summary": "Initiate a new fund transfer",
        "description": "This operation allows users to initiate a fund transfer from one account to another. You need to provide the necessary details such as the sender and receiver account information along with the transfer amount. Upon successful completion, the transfer will be processed and the users will receive a confirmation of their transaction.",
        "operationId": "initiateNewFundTransfer",
        "parameters": [
          {
            "$ref": "#/components/parameters/Authorization"
          },
          {
            "$ref": "#/components/parameters/Content-Type"
          },
          {
            "$ref": "#/components/parameters/x-mock-response"
          }
        ],
        "requestBody": {
          "content": {
            "application/json": {
              "schema": {
                "$ref": "#/components/schemas/InitiateNewFundTransferRequest"
              }
            }
          }
        },
        "responses": {
          "400": {
            "description": "Invalid request parameters provided.",
            "headers": {
              "date": {
                "$ref": "#/components/headers/Date"
              },
              "content-type": {
                "$ref": "#/components/headers/Content-Type"
              }
            },
            "content": {
              "application/json": {
                "schema": {
                  "$ref": "#/components/schemas/InitiateNewFundTransferResponse_400"
                }
              }
            }
          },
          "403": {
            "description": "Access denied for this operation.",
            "headers": {
              "date": {
                "$ref": "#/components/headers/Date"
              },
              "content-type": {
                "$ref": "#/components/headers/Content-Type"
              }
            },
            "content": {
              "application/json": {
                "schema": {
                  "$ref": "#/components/schemas/InitiateNewFundTransferResponse_403"
                }
              }
            }
          },
          "500": {
            "description": "Internal server error occurred.",
            "headers": {
              "date": {
                "$ref": "#/components/headers/Date"
              },
              "content-type": {
                "$ref": "#/components/headers/Content-Type"
              }
            },
            "content": {
              "application/json": {
                "schema": {
                  "$ref": "#/components/schemas/InitiateNewFundTransferResponse_500"
                }
              }
            }
          },
          "200": {
            "description": "Fund transfer initiated successfully.",
            "headers": {
              "date": {
                "$ref": "#/components/headers/Date"
              },
              "content-type": {
                "$ref": "#/components/headers/Content-Type"
              }
            },
            "content": {
              "application/json": {
                "schema": {
                  "$ref": "#/components/schemas/InitiateNewFundTransferResponse_200"
                }
              }
            }
          }
        },
        "callbacks": {},
        "security": [],
        "servers": []
      },
      "servers": [],
      "parameters": []
    }
  },
  "components": {
    "schemas": {
      "InitiateNewFundTransferResponse_400": {
        "type": "object",
        "properties": {
          "errorCode": {
            "type": "string",
            "example": "INVALID_AMOUNT"
          },
          "message": {
            "type": "string",
            "example": "Transfer amount must be greater than zero"
          },
          "details": {
            "type": "string",
            "example": "The field 'amount' contains an invalid value: -250.75"
          },
          "traceId": {
            "type": "string",
            "example": "f4b81d7c9a2e46e6b5c3d8f1a7e9b245"
          }
        },
        "example": {
          "errorCode": "INVALID_AMOUNT",
          "message": "Transfer amount must be greater than zero",
          "details": "The field 'amount' contains an invalid value: -250.75",
          "traceId": "f4b81d7c9a2e46e6b5c3d8f1a7e9b245"
        }
      },
      "InitiateNewFundTransferResponse_403": {
        "type": "object",
        "properties": {
          "errorCode": {
            "type": "string",
            "example": "FORBIDDEN"
          },
          "message": {
            "type": "string",
            "example": "Access to the requested resource is denied"
          },
          "details": {
            "type": "string",
            "example": "The authenticated user does not have permission to perform payment transfers"
          },
          "traceId": {
            "type": "string",
            "example": "7a3d9e5c2f184b8d91c6e4a7f2b5d813"
          }
        },
        "example": {
          "errorCode": "FORBIDDEN",
          "message": "Access to the requested resource is denied",
          "details": "The authenticated user does not have permission to perform payment transfers",
          "traceId": "7a3d9e5c2f184b8d91c6e4a7f2b5d813"
        }
      },
      "InitiateNewFundTransferResponse_500": {
        "type": "object",
        "properties": {
          "errorCode": {
            "type": "string",
            "example": "INTERNAL_SERVER_ERROR"
          },
          "message": {
            "type": "string",
            "example": "An unexpected error occurred while processing the transaction"
          },
          "details": {
            "type": "string",
            "example": "Failed to persist transaction record due to database connection timeout"
          },
          "traceId": {
            "type": "string",
            "example": "c9e27f14b6d8432a8f51e7d394ab6c18"
          }
        },
        "example": {
          "errorCode": "INTERNAL_SERVER_ERROR",
          "message": "An unexpected error occurred while processing the transaction",
          "details": "Failed to persist transaction record due to database connection timeout",
          "traceId": "c9e27f14b6d8432a8f51e7d394ab6c18"
        }
      },
      "InitiateNewFundTransferRequest": {
        "type": "object",
        "properties": {
          "transactionId": {
            "type": "string",
            "example": "DniwUoyVs45vK"
          },
          "sourceAccount": {
            "type": "string",
            "example": "9Q0YWr23Li8U"
          },
          "destinationAccount": {
            "type": "string",
            "example": "74jMku0pzVRx"
          },
          "currency": {
            "type": "string",
            "example": "wec"
          },
          "amount": {
            "type": "number",
            "example": 49.6
          },
          "description": {
            "type": "string",
            "example": "usqqpkuxqvvpsfi"
          }
        },
        "example": "{\n  \"transactionId\" : \"DniwUoyVs45vK\",\n  \"sourceAccount\" : \"9Q0YWr23Li8U\",\n  \"destinationAccount\" : \"74jMku0pzVRx\",\n  \"currency\" : \"wec\",\n  \"amount\" : 49.6,\n  \"description\" : \"usqqpkuxqvvpsfi\"\n}"
      },
      "InitiateNewFundTransferResponse_200": {
        "type": "object",
        "properties": {
          "transactionId": {
            "type": "string",
            "example": "TXN-987654321"
          },
          "status": {
            "type": "string",
            "example": "SUCCESS"
          },
          "referenceId": {
            "type": "string",
            "example": "REF-567890123"
          },
          "amount": {
            "type": "number",
            "example": 250.75
          },
          "currency": {
            "type": "string",
            "example": "USD"
          },
          "processedAt": {
            "type": "string",
            "example": "2026-05-18T06:08:00Z"
          },
          "message": {
            "type": "string",
            "example": "Funds transferred successfully"
          }
        },
        "example": {
          "transactionId": "TXN-987654321",
          "status": "SUCCESS",
          "referenceId": "REF-567890123",
          "amount": 250.75,
          "currency": "USD",
          "processedAt": "2026-05-18T06:08:00Z",
          "message": "Funds transferred successfully"
        }
      }
    },
    "parameters": {
      "Authorization": {
        "name": "Authorization",
        "in": "header",
        "required": false,
        "style": "simple",
        "explode": false,
        "schema": {
          "type": "string",
          "example": "Bearer invalid-or-expired-token"
        },
        "example": "Bearer invalid-or-expired-token"
      },
      "Content-Type": {
        "name": "Content-Type",
        "in": "header",
        "required": false,
        "style": "simple",
        "explode": false,
        "schema": {
          "type": "string",
          "example": "application/json"
        },
        "example": "application/json"
      },
      "x-mock-response": {
        "name": "x-mock-response",
        "in": "header",
        "description": "Controls x-mock-response response status",
        "required": false,
        "style": "simple",
        "explode": false,
        "schema": {
          "type": "string",
          "enum": [
            "bad_request",
            "forbidden",
            "server_error",
            "success"
          ]
        }
      }
    },
    "headers": {
      "Date": {
        "style": "simple",
        "explode": false,
        "schema": {
          "type": "string",
          "example": "G4dCuDEsoECKWDczFDxfJ8CIaTO94"
        },
        "example": "G4dCuDEsoECKWDczFDxfJ8CIaTO94"
      },
      "Content-Type": {
        "style": "simple",
        "explode": false,
        "schema": {
          "type": "string",
          "example": "4'9t'5sY1'57ylwZ"
        },
        "example": "4'9t'5sY1'57ylwZ"
      }
    }
  }
}