{
  "openapi": "3.0.1",
  "info": {
    "title": "Stock Transfer Approval API",
    "description": "Stock Transfer Approval API",
    "version": "1.0",
    "extensions": {
      "x-oas-type": "Runtime"
    }
  },
  "servers": [
    {
      "url": "https://stage-data-gujl.apiwiz.io/v1/inventory",
      "variables": {},
      "x-schema": "https://",
      "x-name": "Sandbox server",
      "x-environmentName": "DEV",
      "x-hide": false,
      "x-environmentId": "688884305134cd49a9bcfec3",
      "x-basePath": "/v1/inventory"
    }
  ],
  "paths": {
    "/stock/transfer/warehouse/source/destination/approval/initiate": {
      "put": {
        "operationId": "PUT_stock_transfer_warehouse_source_destination_approval_initiate",
        "parameters": [
          {
            "$ref": "#/components/parameters/Content-Type"
          },
          {
            "$ref": "#/components/parameters/parentspanid"
          },
          {
            "$ref": "#/components/parameters/Authorization"
          },
          {
            "$ref": "#/components/parameters/X-Approval-Id"
          },
          {
            "$ref": "#/components/parameters/X-Warehouse-Id"
          }
        ],
        "requestBody": {
          "content": {
            "application/json": {
              "schema": {
                "$ref": "#/components/schemas/PUT_stock_transfer_warehouse_source_destination_approval_initiateRequest"
              }
            }
          }
        },
        "responses": {
          "500": {
            "description": "500Description",
            "headers": {
              "Date": {
                "$ref": "#/components/headers/Date"
              },
              "X-Trace-Id": {
                "$ref": "#/components/headers/X-Trace-Id"
              },
              "Content-Type": {
                "$ref": "#/components/headers/Content-Type"
              }
            },
            "content": {
              "application/json": {
                "schema": {
                  "$ref": "#/components/schemas/PUT_stock_transfer_warehouse_source_destination_approval_initiateResponse_500"
                }
              }
            }
          },
          "400": {
            "description": "400Description",
            "headers": {
              "Date": {
                "$ref": "#/components/headers/Date"
              },
              "X-Trace-Id": {
                "$ref": "#/components/headers/X-Trace-Id"
              },
              "Content-Type": {
                "$ref": "#/components/headers/Content-Type"
              }
            },
            "content": {
              "application/json": {
                "schema": {
                  "$ref": "#/components/schemas/PUT_stock_transfer_warehouse_source_destination_approval_initiateResponse_400"
                }
              }
            }
          },
          "200": {
            "description": "Resource updated successfully",
            "headers": {
              "Date": {
                "$ref": "#/components/headers/Date"
              },
              "X-Trace-Id": {
                "$ref": "#/components/headers/X-Trace-Id"
              },
              "Content-Type": {
                "$ref": "#/components/headers/Content-Type"
              }
            },
            "content": {
              "application/json": {
                "schema": {
                  "$ref": "#/components/schemas/PUT_stock_transfer_warehouse_source_destination_approval_initiateResponse_200"
                }
              }
            }
          }
        },
        "callbacks": {},
        "security": [],
        "servers": []
      },
      "servers": [],
      "parameters": []
    }
  },
  "components": {
    "schemas": {
      "PUT_stock_transfer_warehouse_source_destination_approval_initiateResponse_500": {
        "type": "object",
        "properties": {
          "error": {
            "type": "string",
            "example": "WMS_INTEGRATION_ERROR"
          },
          "code": {
            "type": "integer",
            "format": "int32",
            "example": 500
          },
          "message": {
            "type": "integer",
            "format": "int32",
            "example": 83893
          },
          "incidentId": {
            "type": "integer",
            "format": "int32",
            "example": 46189
          },
          "retryAfter": {
            "type": "integer",
            "format": "int32",
            "example": 60
          },
          "timestamp": {
            "type": "integer",
            "format": "int32",
            "example": 22429
          }
        },
        "example": {
          "error": "WMS_INTEGRATION_ERROR",
          "code": 500,
          "message": 83893,
          "incidentId": 46189,
          "retryAfter": 60,
          "timestamp": 22429
        }
      },
      "PUT_stock_transfer_warehouse_source_destination_approval_initiateResponse_400": {
        "type": "object",
        "properties": {
          "error": {
            "type": "integer",
            "format": "int32",
            "example": 68897
          },
          "code": {
            "type": "integer",
            "format": "int32",
            "example": 400
          },
          "details": {
            "type": "array",
            "example": [
              "Source and destination warehouse cannot be the same",
              "Transfer quantity 500 exceeds available stock of 48 for SKU-ELEC-1001",
              "approvalId is required for transfers above 30 units",
              "scheduledDate is required"
            ],
            "items": {
              "type": "string",
              "example": "xpyeljptofkaotjxrcpobpeazuvnylpsjbuzzfukqjxemkxoyhq"
            }
          },
          "timestamp": {
            "type": "integer",
            "format": "int32",
            "example": 32370
          }
        },
        "example": {
          "error": 68897,
          "code": 400,
          "details": [
            "Source and destination warehouse cannot be the same",
            "Transfer quantity 500 exceeds available stock of 48 for SKU-ELEC-1001",
            "approvalId is required for transfers above 30 units",
            "scheduledDate is required"
          ],
          "timestamp": 32370
        }
      },
      "PUT_stock_transfer_warehouse_source_destination_approval_initiateRequest": {
        "type": "object",
        "properties": {
          "sourceWarehouseId": {
            "type": "string",
            "example": "TuFvMUyObQnm"
          },
          "destinationWarehouseId": {
            "type": "integer",
            "format": "int32",
            "example": 73
          },
          "items": {
            "type": "array",
            "example": "[ {\n  \"sku\" : \"Susl7Psrfn4u3\",\n  \"quantity\" : 64\n}, {\n  \"sku\" : \"4TC91v4gf1AGb\",\n  \"quantity\" : 33\n} ]",
            "items": {
              "type": "object",
              "properties": {
                "sku": {
                  "type": "string",
                  "example": "Susl7Psrfn4u3"
                },
                "quantity": {
                  "type": "integer",
                  "format": "int32",
                  "example": 64
                }
              },
              "example": "{\n  \"sku\" : \"Susl7Psrfn4u3\",\n  \"quantity\" : 64\n}"
            }
          },
          "transferReason": {
            "type": "string",
            "example": "x'ulZbpk+igl2Zxj"
          },
          "scheduledDate": {
            "type": "string",
            "example": ")G?s!Dq^D$"
          },
          "carrierId": {
            "type": "integer",
            "format": "int32",
            "example": 47
          },
          "approvalId": {
            "type": "string",
            "example": "x6GWBl2CyWvGG"
          },
          "priority": {
            "type": "integer",
            "format": "int32",
            "example": 53
          }
        },
        "example": "{\n  \"sourceWarehouseId\" : \"TuFvMUyObQnm\",\n  \"destinationWarehouseId\" : 73,\n  \"items\" : [ {\n    \"sku\" : \"Susl7Psrfn4u3\",\n    \"quantity\" : 64\n  }, {\n    \"sku\" : \"4TC91v4gf1AGb\",\n    \"quantity\" : 33\n  } ],\n  \"transferReason\" : \"x'ulZbpk+igl2Zxj\",\n  \"scheduledDate\" : \")G?s!Dq^D$\",\n  \"carrierId\" : 47,\n  \"approvalId\" : \"x6GWBl2CyWvGG\",\n  \"priority\" : 53\n}"
      },
      "PUT_stock_transfer_warehouse_source_destination_approval_initiateResponse_200": {
        "type": "object",
        "properties": {
          "transferId": {
            "type": "integer",
            "format": "int32",
            "example": 79887
          },
          "status": {
            "type": "string",
            "example": "APPROVED"
          },
          "sourceWarehouse": {
            "type": "integer",
            "format": "int32",
            "example": 35708
          },
          "destinationWarehouse": {
            "type": "string",
            "example": "WH-SOUTH-007"
          },
          "itemsToTransfer": {
            "type": "integer",
            "format": "int32",
            "example": 2
          },
          "totalUnits": {
            "type": "integer",
            "format": "int32",
            "example": 70
          },
          "scheduledDate": {
            "type": "string",
            "example": "2026-06-09"
          },
          "estimatedArrival": {
            "type": "string",
            "example": "2026-06-10"
          },
          "shippingLabel": {
            "type": "integer",
            "format": "int32",
            "example": 65551
          },
          "message": {
            "type": "string",
            "example": "Stock transfer approved and scheduled"
          }
        },
        "example": {
          "transferId": 79887,
          "status": "APPROVED",
          "sourceWarehouse": 35708,
          "destinationWarehouse": "WH-SOUTH-007",
          "itemsToTransfer": 2,
          "totalUnits": 70,
          "scheduledDate": "2026-06-09",
          "estimatedArrival": "2026-06-10",
          "shippingLabel": 65551,
          "message": "Stock transfer approved and scheduled"
        }
      }
    },
    "parameters": {
      "Content-Type": {
        "name": "Content-Type",
        "in": "header",
        "required": false,
        "style": "simple",
        "explode": false,
        "schema": {
          "type": "string",
          "example": "application/json"
        },
        "example": "application/json"
      },
      "parentspanid": {
        "name": "parentspanid",
        "in": "header",
        "required": false,
        "style": "simple",
        "explode": false,
        "schema": {
          "type": "string",
          "example": "c64017b657b2414a8526cd4578536eb0094dc7a5b09b4887"
        },
        "example": "c64017b657b2414a8526cd4578536eb0094dc7a5b09b4887"
      },
      "Authorization": {
        "name": "Authorization",
        "in": "header",
        "required": false,
        "style": "simple",
        "explode": false,
        "schema": {
          "type": "string",
          "example": "Bearer warehouse-mgr-token"
        },
        "example": "Bearer warehouse-mgr-token"
      },
      "X-Approval-Id": {
        "name": "X-Approval-Id",
        "in": "header",
        "required": false,
        "style": "simple",
        "explode": false,
        "schema": {
          "type": "string",
          "example": "APRV-INV-7721"
        },
        "example": "APRV-INV-7721"
      },
      "X-Warehouse-Id": {
        "name": "X-Warehouse-Id",
        "in": "header",
        "required": false,
        "style": "simple",
        "explode": false,
        "schema": {
          "type": "string",
          "example": "WH-NORTH-003"
        },
        "example": "WH-NORTH-003"
      }
    },
    "headers": {
      "Date": {
        "style": "simple",
        "explode": false,
        "schema": {
          "type": "string",
          "example": "Mon, 08 Jun 2026 10:00:00 GMT"
        },
        "example": "Mon, 08 Jun 2026 10:00:00 GMT"
      },
      "X-Trace-Id": {
        "style": "simple",
        "explode": false,
        "schema": {
          "type": "string",
          "example": "22d36927ff21483e8decec87feaa7fd4e6d04596b46e49c0"
        },
        "example": "22d36927ff21483e8decec87feaa7fd4e6d04596b46e49c0"
      },
      "Content-Type": {
        "style": "simple",
        "explode": false,
        "schema": {
          "type": "string",
          "example": "application/json"
        },
        "example": "application/json"
      }
    }
  }
}